stdlib/_ast.pyi
stdlib/_codecs.pyi
stdlib/_collections_abc.pyi
stdlib/_typeshed/__init__.pyi
stdlib/_typeshed/dbapi.pyi
stdlib/_typeshed/wsgi.pyi
stdlib/_typeshed/xml.pyi
stdlib/builtins.pyi
stdlib/codecs.pyi
stdlib/collections/__init__.pyi
stdlib/collections/abc.pyi
stdlib/io.pyi
stdlib/os/__init__.pyi
stdlib/os/path.pyi
stdlib/sys.pyi
stdlib/types.pyi
stdlib/typing.pyi
stdlib/typing_extensions.pyi
micropython_stdlib_minimal-1.0.0.dist-info/LICENSE.md
micropython_stdlib_minimal-1.0.0.dist-info/WHEEL
micropython_stdlib_minimal-1.0.0.dist-info/METADATA
micropython_stdlib_minimal-1.0.0.dist-info/RECORD
